{
  "classesInSubtitle": "Classes",
  "structsInSubtitle": "Structs",
  "interfacesInSubtitle": "Interfaces",
  "enumsInSubtitle": "Enums",
  "delegatesInSubtitle": "Delegates",
  "constructorsInSubtitle": "Constructors",
  "fieldsInSubtitle": "Fields",
  "propertiesInSubtitle": "Properties",
  "methodsInSubtitle": "Methods",
  "eventsInSubtitle": "Events",
  "operatorsInSubtitle": "Operators",
  "important": "<h5>Důležité</h5>",
  "note": "<h5>Poznámka</h5>",
  "tip": "<h5>Tip</h5>",
  "caution": "<h5>Upozornění</h5>",
  "warning": "<h5>Upozornění</h5>"
}